wasd3r/__init__.py
wasd3r/chains/__init__ copy.py
wasd3r/chains/__init__.py
wasd3r/chains/aptos/__init__.py
wasd3r/chains/aptos/chain_info.py
wasd3r/chains/aptos/comms.py
wasd3r/chains/aptos/contract.py
wasd3r/chains/chain_info.py
wasd3r/chains/comms.py
wasd3r/chains/contract.py
wasd3r/chains/exceptions.py
wasd3r_sdk-0.0.2.dist-info/WHEEL
wasd3r_sdk-0.0.2.dist-info/METADATA
wasd3r_sdk-0.0.2.dist-info/RECORD
