Metadata-Version: 2.1
Name: wasd3r-sdk
Version: 0.0.2
Summary: Wasd3r standard dev kit
Author: Aaron
Author-email: aaron@wasd3r.xyz
Maintainer: Aaron
Maintainer-email: aaron@wasd3r.xyz
Requires-Python: >=3.8.1,<4.0.0
Classifier: Programming Language :: Python :: 3
Classifier: Programming Language :: Python :: 3.9
Classifier: Programming Language :: Python :: 3.10
Classifier: Programming Language :: Python :: 3.11
Provides-Extra: aptos
Requires-Dist: aptos-sdk (>=0.4.1,<0.5.0); extra == "aptos"
Requires-Dist: black (==22.10.0)
Requires-Dist: flake8 (>=6.0.0,<7.0.0)
Requires-Dist: isort (==5.10.1)
Requires-Dist: pytest (==7.2.0)
